chinaunicom_agent/__init__.py
chinaunicom_agent/week_report.py
chinaunicom_agent-0.4.1.dist-info/licenses/LICENSE
chinaunicom_agent-0.4.1.dist-info/METADATA
chinaunicom_agent-0.4.1.dist-info/WHEEL
chinaunicom_agent-0.4.1.dist-info/top_level.txt
chinaunicom_agent-0.4.1.dist-info/RECORD
